MANIFEST.in
README.md
setup.py
version.py
myreco/__init__.py
myreco/api.py
myreco/authorizer.py
myreco/exceptions.py
myreco/factory.py
myreco/utils.py
myreco.egg-info/PKG-INFO
myreco.egg-info/SOURCES.txt
myreco.egg-info/dependency_links.txt
myreco.egg-info/requires.txt
myreco.egg-info/top_level.txt
myreco/engine_objects/__init__.py
myreco/engine_objects/model.py
myreco/engine_objects/object_base.py
myreco/engine_objects/swagger.json
myreco/engine_objects/data_importer/__init__.py
myreco/engine_objects/data_importer/model.py
myreco/engine_objects/data_importer/swagger.json
myreco/engine_objects/exporter/__init__.py
myreco/engine_objects/exporter/model.py
myreco/engine_objects/exporter/swagger.json
myreco/engine_strategies/__init__.py
myreco/engine_strategies/model.py
myreco/engine_strategies/strategy_base.py
myreco/engine_strategies/swagger.json
myreco/engine_strategies/filters/__init__.py
myreco/engine_strategies/filters/apply_filters.c
myreco/engine_strategies/filters/factory.py
myreco/engine_strategies/filters/filters.py
myreco/engine_strategies/top_seller/__init__.py
myreco/engine_strategies/top_seller/_recommender.c
myreco/engine_strategies/top_seller/array.py
myreco/engine_strategies/top_seller/strategy.py
myreco/engines/__init__.py
myreco/engines/model.py
myreco/engines/swagger.json
myreco/external_variables/__init__.py
myreco/external_variables/model.py
myreco/external_variables/swagger.json
myreco/item_types/__init__.py
myreco/item_types/_store_items_model_meta.py
myreco/item_types/indices_map.py
myreco/item_types/model.py
myreco/item_types/store_items_metaschema.json
myreco/item_types/swagger.json
myreco/item_types/data_file_importer/__init__.py
myreco/item_types/data_file_importer/model.py
myreco/item_types/data_file_importer/swagger.json
myreco/item_types/filters_updater/__init__.py
myreco/item_types/filters_updater/model.py
myreco/item_types/filters_updater/swagger.json
myreco/placements/__init__.py
myreco/placements/models.py
myreco/placements/swagger.json
myreco/slots/__init__.py
myreco/slots/models.py
myreco/slots/swagger.json
myreco/stores/__init__.py
myreco/stores/model.py
