Metadata-Version: 1.1
Name: myreco
Version: 0.65.5
Summary: A Recommendations Framework
Home-page: https://github.com/dutradda/myreco
Author: Diogo Dutra
Author-email: dutradda@gmail.com
License: MIT
Download-URL: http://github.com/dutradda/myreco/archive/master.tar.gz
Keywords: recommendations neighborhood visualsimilarity visual similarity topseller top seller swagger openapi falconframework falcon framework
Platform: UNKNOWN
Classifier: License :: OSI Approved :: MIT License
Classifier: Development Status :: 4 - Beta
Classifier: Intended Audience :: Developers
Classifier: Natural Language :: English
Classifier: Programming Language :: Python :: 3.5
Classifier: Topic :: Internet :: WWW/HTTP :: WSGI :: Middleware
Classifier: Topic :: Software Development :: Libraries :: Python Modules
